explorepy/BLEClient.py
explorepy/BTClient.py
explorepy/__init__.py
explorepy/_exceptions.py
explorepy/bt_mock_client.py
explorepy/bt_mock_server.py
explorepy/cli.py
explorepy/command.py
explorepy/debug.py
explorepy/explore.py
explorepy/filters.py
explorepy/log_config.py
explorepy/packet.py
explorepy/parser.py
explorepy/serial_client.py
explorepy/settings_manager.py
explorepy/stream_processor.py
explorepy/tools.py
explorepy-4.3.1.dist-info/licenses/AUTHORS.rst
explorepy-4.3.1.dist-info/licenses/LICENSE
explorepy-4.3.1.dist-info/METADATA
explorepy-4.3.1.dist-info/WHEEL
explorepy-4.3.1.dist-info/entry_points.txt
explorepy-4.3.1.dist-info/top_level.txt
explorepy-4.3.1.dist-info/RECORD
