Metadata-Version: 2.4
Name: explorepy
Version: 4.3.1
Author-email: MentaLab Hub <support@mentab.org>
License: MIT
Project-URL: Homepage, https://github.com/Mentalab-hub/explorepy
Classifier: Development Status :: 5 - Production/Stable
Classifier: Intended Audience :: Developers
Classifier: Intended Audience :: Science/Research
Classifier: License :: OSI Approved :: MIT License
Classifier: Programming Language :: Python :: 3
Classifier: Programming Language :: Python :: 3.10
Classifier: Programming Language :: Python :: 3.11
Classifier: Programming Language :: Python :: 3.12
Classifier: Operating System :: OS Independent
Classifier: Operating System :: MacOS
Classifier: Operating System :: Microsoft :: Windows
Classifier: Operating System :: POSIX :: Linux
Classifier: Topic :: Scientific/Engineering :: Information Analysis
Classifier: Topic :: Software Development :: Libraries :: Python Modules
License-File: LICENSE
License-File: AUTHORS.rst
Requires-Dist: numpy
Requires-Dist: scipy
Requires-Dist: pyEDFlib==0.1.38
Requires-Dist: click==7.1.2
Requires-Dist: appdirs==1.4.3
Requires-Dist: sentry_sdk==2.8.0
Requires-Dist: mne
Requires-Dist: eeglabio
Requires-Dist: pandas
Requires-Dist: pyserial
Requires-Dist: pyyaml
Requires-Dist: bleak==0.22.3
Requires-Dist: pylsl
Requires-Dist: numba
Provides-Extra: test
Requires-Dist: pytest==6.2.5; extra == "test"
Requires-Dist: pytest-mock==3.10.0; extra == "test"
Requires-Dist: pytest-html==3.2.0; extra == "test"
Requires-Dist: flake8==4.0.1; extra == "test"
Requires-Dist: isort==5.10.1; extra == "test"
Dynamic: license-file
